Metadata-Version: 2.1
Name: trainer-py
Version: 0.2.0
Summary: Lightweight context-based library for benchmarking
Home-page: https://github.com/MichalMoravik/trainer
License: MIT
Keywords: metrics,benchmark
Platform: UNKNOWN
Classifier: Programming Language :: Python
Classifier: Programming Language :: Python :: 3
Classifier: Programming Language :: Python :: 3 :: Only
License-File: LICENSE
